tobe_time_mcp/__init__.py
tobe_time_mcp/server.py
tobe_time_mcp-0.1.0.dist-info/METADATA
tobe_time_mcp-0.1.0.dist-info/WHEEL
tobe_time_mcp-0.1.0.dist-info/entry_points.txt
tobe_time_mcp-0.1.0.dist-info/top_level.txt
tobe_time_mcp-0.1.0.dist-info/RECORD
