Metadata-Version: 2.4
Name: tobe-time-mcp
Version: 0.1.0
Summary: The MCP server to get local time
Requires-Python: >=3.12
Requires-Dist: fastmcp>=2.7.0
